clayPlotter/__init__.py
clayPlotter/__version__.py
clayPlotter/data_loader.py
clayPlotter/geo_data_manager.py
clayPlotter/plotter.py
clayPlotter/resources/brazil_states.yaml
clayPlotter/resources/canada_provinces.yaml
clayPlotter/resources/china_provinces.yaml
clayPlotter/resources/usa_states.yaml
clayplotter-0.1.0.dist-info/licenses/LICENSE
clayplotter-0.1.0.dist-info/METADATA
clayplotter-0.1.0.dist-info/WHEEL
clayplotter-0.1.0.dist-info/top_level.txt
clayplotter-0.1.0.dist-info/RECORD
