Metadata-Version: 2.4
Name: clayPlotter
Version: 0.1.0
Summary: A Python package for creating configurable choropleth maps.
Author-email: Clay <claytoneyoung+clayPlotter@gmail.com>
License: MIT
Project-URL: Homepage, https://github.com/borealByte/clayPlotter
Project-URL: Repository, https://github.com/borealByte/clayPlotter
Classifier: Development Status :: 3 - Alpha
Classifier: Intended Audience :: Science/Research
Classifier: Programming Language :: Python :: 3
Classifier: Programming Language :: Python :: 3.10
Classifier: Programming Language :: Python :: 3.11
Classifier: Programming Language :: Python :: 3.12
Classifier: Topic :: Scientific/Engineering :: GIS
Classifier: Topic :: Scientific/Engineering :: Visualization
Requires-Python: >=3.10
License-File: LICENSE
Requires-Dist: geopandas>=0.13.0
Requires-Dist: matplotlib>=3.7.0
Requires-Dist: pandas>=1.5.0
Requires-Dist: PyYAML>=6.0
Requires-Dist: shapely>=2.0
Requires-Dist: requests>=2.28.0
Provides-Extra: dev
Requires-Dist: jupyter>=1.0.0; extra == "dev"
Requires-Dist: nbconvert>=7.0.0; extra == "dev"
Requires-Dist: pytest>=7.0.0; extra == "dev"
Requires-Dist: build>=0.10.0; extra == "dev"
Requires-Dist: twine>=4.0.0; extra == "dev"
Dynamic: license-file
